hlpl_templater/__init__.py
hlpl_templater/__main__.py
hlpl_templater/setup.cfg
hlpl_templater-1.0.0.dist-info/LICENSE
hlpl_templater-1.0.0.dist-info/METADATA
hlpl_templater-1.0.0.dist-info/WHEEL
hlpl_templater-1.0.0.dist-info/entry_points.txt
hlpl_templater-1.0.0.dist-info/top_level.txt
hlpl_templater-1.0.0.dist-info/RECORD
