Metadata-Version: 2.1
Name: hlpl-templater
Version: 1.0.0
Summary: Text templater
Home-page: https://templater.hlpl.net
Author: Ahmida Bendjoudi
Author-email: email@hlpl.net
License: MIT
Download-URL: https://templater.hlpl.net/download/
Project-URL: hlpl, https://hlpl.net
Project-URL: hlpl_templater-docs, https://docs.hlpl.net
Project-URL: hlpl_templater-forum, https://forum.hlpl.net
Project-URL: hlpl_templater-resource, https://resource.hlpl.net
Project-URL: hlpl_templater-github, https://github.com/hlpl/templater
Keywords: hlpl_templater,hlpl templater,hlpl-templater,text templater,hlpl
Platform: UNKNOWN
Classifier: Framework :: Robot Framework
Classifier: Framework :: Robot Framework :: Library
Classifier: Framework :: Robot Framework :: Tool
Classifier: Natural Language :: Arabic
Classifier: Natural Language :: English
Requires-Python: >=3, <=3.9
